putplace_client/__init__.py
putplace_client/ppclient.py
putplace_client/version.py
putplace_client-0.8.4.dist-info/METADATA
putplace_client-0.8.4.dist-info/WHEEL
putplace_client-0.8.4.dist-info/entry_points.txt
putplace_client-0.8.4.dist-info/RECORD
