Metadata-Version: 2.4
Name: putplace-client
Version: 0.8.4
Summary: PutPlace CLI client for scanning directories and uploading file metadata
License: Apache-2.0
Classifier: Development Status :: 4 - Beta
Classifier: Intended Audience :: Developers
Classifier: Intended Audience :: System Administrators
Classifier: License :: OSI Approved :: Apache Software License
Classifier: Programming Language :: Python :: 3
Classifier: Programming Language :: Python :: 3.10
Classifier: Programming Language :: Python :: 3.11
Classifier: Programming Language :: Python :: 3.12
Classifier: Programming Language :: Python :: 3.13
Classifier: Programming Language :: Python :: 3.14
Classifier: Topic :: System :: Archiving
Classifier: Topic :: System :: Filesystems
Classifier: Topic :: System :: Systems Administration
Requires-Python: >=3.10
Requires-Dist: configargparse>=1.7.0
Requires-Dist: httpx>=0.26.0
Requires-Dist: rich>=13.7.0
Provides-Extra: dev
Requires-Dist: pytest-cov>=4.1.0; extra == 'dev'
Requires-Dist: pytest>=8.0.0; extra == 'dev'
Requires-Dist: ruff>=0.3.0; extra == 'dev'
